_voronoi.cpython-311-aarch64-linux-musl.so
voronoi/diagram.py
voronoi/big_float.py
voronoi/point.py
voronoi/enums.py
voronoi/big_int.py
voronoi/builder.py
voronoi/utils.py
voronoi/robust_difference.py
voronoi/__init__.py
voronoi/beach_line_value.py
voronoi/robust_float.py
voronoi/segment.py
voronoi/beach_line_key.py
voronoi/faces.py
voronoi/events/computers.py
voronoi/events/__init__.py
voronoi/events/predicates.py
voronoi/events/models.py
voronoi.libs/libstdc++-fd9f4683.so.6.0.28
voronoi.libs/libgcc_s-4e37474d.so.1
voronoi-0.4.0.dist-info/LICENSE
voronoi-0.4.0.dist-info/WHEEL
voronoi-0.4.0.dist-info/top_level.txt
voronoi-0.4.0.dist-info/RECORD
voronoi-0.4.0.dist-info/METADATA
